LICENSE
MANIFEST.in
README.rst
setup.py
bootstrap_form_horizontal/__init__.py
bootstrap_form_horizontal/static/bootstrap_form_horizontal/datewidgets.js
bootstrap_form_horizontal/static/bootstrap_form_horizontal/vendor/bootstrap/version.txt
bootstrap_form_horizontal/static/bootstrap_form_horizontal/vendor/bootstrap/css/bootstrap-theme.css
bootstrap_form_horizontal/static/bootstrap_form_horizontal/vendor/bootstrap/css/bootstrap-theme.css.map
bootstrap_form_horizontal/static/bootstrap_form_horizontal/vendor/bootstrap/css/bootstrap-theme.min.css
bootstrap_form_horizontal/static/bootstrap_form_horizontal/vendor/bootstrap/css/bootstrap.css
bootstrap_form_horizontal/static/bootstrap_form_horizontal/vendor/bootstrap/css/bootstrap.css.map
bootstrap_form_horizontal/static/bootstrap_form_horizontal/vendor/bootstrap/css/bootstrap.min.css
bootstrap_form_horizontal/static/bootstrap_form_horizontal/vendor/bootstrap/fonts/glyphicons-halflings-regular.eot
bootstrap_form_horizontal/static/bootstrap_form_horizontal/vendor/bootstrap/fonts/glyphicons-halflings-regular.svg
bootstrap_form_horizontal/static/bootstrap_form_horizontal/vendor/bootstrap/fonts/glyphicons-halflings-regular.ttf
bootstrap_form_horizontal/static/bootstrap_form_horizontal/vendor/bootstrap/fonts/glyphicons-halflings-regular.woff
bootstrap_form_horizontal/static/bootstrap_form_horizontal/vendor/bootstrap/js/bootstrap.js
bootstrap_form_horizontal/static/bootstrap_form_horizontal/vendor/bootstrap/js/bootstrap.min.js
bootstrap_form_horizontal/static/bootstrap_form_horizontal/vendor/bootstrap/js/npm.js
bootstrap_form_horizontal/static/bootstrap_form_horizontal/vendor/pikaday/CHANGELOG.md
bootstrap_form_horizontal/static/bootstrap_form_horizontal/vendor/pikaday/LICENSE
bootstrap_form_horizontal/static/bootstrap_form_horizontal/vendor/pikaday/README.md
bootstrap_form_horizontal/static/bootstrap_form_horizontal/vendor/pikaday/pikaday.js
django_bootstrap_form_horizontal.egg-info/PKG-INFO
django_bootstrap_form_horizontal.egg-info/SOURCES.txt
django_bootstrap_form_horizontal.egg-info/dependency_links.txt
django_bootstrap_form_horizontal.egg-info/top_level.txt