Metadata-Version: 1.1
Name: django-bootstrap-form-horizontal
Version: 0.0.3
Summary: Templates for bootstrap3 style horizontal forms in Django
Home-page: https://github.com/yourcelf/django-bootstrap-form-horizontal
Author: Charlie DeTar
Author-email: cfd@media.mit.edu
License: BSD License
Platform: UNKNOWN
Classifier: Environment :: Web Environment
Classifier: Framework :: Django
Classifier: Intended Audience :: Developers
Classifier: License :: OSI Approved :: BSD License
Classifier: Operating System :: OS Independent
Classifier: Programming Language :: Python
Classifier: Topic :: Internet :: WWW/HTTP
Classifier: Topic :: Internet :: WWW/HTTP :: Dynamic Content
